efficientnet/__init__.py
efficientnet/__version__.py
efficientnet/keras.py
efficientnet/model.py
efficientnet/preprocessing.py
efficientnet/tfkeras.py
efficientnet/weights.py
efficientnet-1.1.0.dist-info/LICENSE
efficientnet-1.1.0.dist-info/METADATA
efficientnet-1.1.0.dist-info/WHEEL
efficientnet-1.1.0.dist-info/top_level.txt
efficientnet-1.1.0.dist-info/RECORD
