Metadata-Version: 2.1
Name: efficientnet
Version: 1.1.0
Summary: EfficientNet model re-implementation. Keras and TensorFlow Keras.
Home-page: https://github.com/qubvel/efficientnet
Author: Pavel Yakubovskiy
Author-email: qubvel@gmail.com
License: Apache License 2.0
Platform: UNKNOWN
Classifier: License :: OSI Approved :: Apache Software License
Classifier: Programming Language :: Python
Classifier: Programming Language :: Python :: 3
Classifier: Programming Language :: Python :: Implementation :: CPython
Classifier: Programming Language :: Python :: Implementation :: PyPy
Requires-Python: >=3.0.0
Requires-Dist: keras-applications (<=1.0.8,>=1.0.7)
Requires-Dist: scikit-image
Provides-Extra: test
Requires-Dist: pytest ; extra == 'test'
